itchat_desktop/__init__.py
itchat_desktop/components.py
itchat_desktop/patch.py
itchat_desktop-1.2.dist-info/METADATA
itchat_desktop-1.2.dist-info/WHEEL
itchat_desktop-1.2.dist-info/top_level.txt
itchat_desktop-1.2.dist-info/RECORD
