Metadata-Version: 2.1
Name: itchat-desktop
Version: 1.2
Summary: wechat sdk
Home-page: https://github.com/eatmoreapple/itchat_desktop
Author: eatmoreapple
Author-email: eatmoreorange@gmail.com
License: MIT Licence
Platform: any
Requires-Dist: itchat
